{
  "products": [
    {
      "id": 1,
      "name": "Product001",
      "description": "This is a description for Product001.",
      "price": 15,
      "image": "product001.jpg"
    },
    {
      "id": 2,
      "name": "Product002",
      "description": "This is a description for Product002.",
      "price": 15,
      "image": "product002.jpg"
    },
    {
      "id": 3,
      "name": "Product003",
      "description": "This is a description for Product003.",
      "price": 15,
      "image": "product003.jpg"
    },
    {
      "id": 4,
      "name": "Product004",
      "description": "This is a description for Product004.",
      "price": 15,
      "image": "product004.jpg"
    },
    {
      "id": 5,
      "name": "Product005",
      "description": "This is a description for Product005.",
      "price": 55,
      "image": "product005.jpg"
    },
    {
      "id": 6,
      "name": "Product006",
      "description": "This is a description for Product006.",
      "price": 65,
      "image": "product006.jpg"
    },
    {
      "id": 7,
      "name": "Product007",
      "description": "This is a description for Product007.",
      "price": 75,
      "image": "product007.jpg"
    },
    {
      "id": 8,
      "name": "Product008",
      "description": "This is a description for Product008.",
      "price": 85,
      "image": "product008.jpg"
    },
    {
      "id": 9,
      "name": "Product009",
      "description": "This is a description for Product009.",
      "price": 95,
      "image": "product009.jpg"
    },
    {
      "id": 10,
      "name": "Product010",
      "description": "This is a description for Product010.",
      "price": 105,
      "image": "product010.jpg"
    }
  ],
  "sales": [
    {
      "id": 1,
      "productId": 1,
      "quantity": 5,
      "customerId": 1
    },
    {
      "id": 2,
      "productId": 2,
      "quantity": 3,
      "customerId": 2
    },
    {
      "id": 3,
      "productId": 3,
      "quantity": 2,
      "customerId": 3
    },
    {
      "id": 4,
      "productId": 4,
      "quantity": 7,
      "customerId": 4
    },
    {
      "id": 5,
      "productId": 5,
      "quantity": 4,
      "customerId": 5
    }
  ],
  "customers": [
    {
      "id": 1,
      "name": "Customer001",
      "email": "customer001@example.com"
    },
    {
      "id": 2,
      "name": "Customer002",
      "email": "customer002@example.com"
    },
    {
      "id": 3,
      "name": "Customer003",
      "email": "customer003@example.com"
    },
    {
      "id": 4,
      "name": "Customer004",
      "email": "customer004@example.com"
    },
    {
      "id": 5,
      "name": "Customer005",
      "email": "customer005@example.com"
    }
  ]
}
